university_scraper/__init__.py
university_scraper/__version__.py
university_scraper/_abstract.py
university_scraper/universities/__init__.py
university_scraper/universities/usyd.py
university_scraper/utils/__init__.py
university_scraper/utils/crawler.py
university_scraper/utils/formatters.py
university_scraper/utils/scraper.py
university_scraper-0.0.2.dist-info/LICENSE
university_scraper-0.0.2.dist-info/METADATA
university_scraper-0.0.2.dist-info/WHEEL
university_scraper-0.0.2.dist-info/top_level.txt
university_scraper-0.0.2.dist-info/RECORD
