Metadata-Version: 2.1
Name: university-scraper
Version: 0.0.2
Summary: Python package for scraping university information
Home-page: https://github.com/giulianocelani/university-scraper/
Author: Giuliano Celani
Author-email: giuliano_celani@hotmail.com
License: UNKNOWN
Keywords: python uni university scraper uni-scraper university-scraper uni-scrapers university-scrapers
Platform: UNKNOWN
Classifier: Programming Language :: Python :: 3
Classifier: License :: OSI Approved :: MIT License
Classifier: Intended Audience :: Developers
Classifier: Operating System :: OS Independent
Classifier: Topic :: Internet :: WWW/HTTP
Requires-Python: >=3.6
Requires-Dist: beautifulsoup4 (>=4.9.0)
Requires-Dist: selenium (>=3.141.0)
Requires-Dist: webdriver-manager (>=3.2.2)
Requires-Dist: requests (>=2.23.0)
Requires-Dist: lxml (>=4.5.0)
Requires-Dist: tabulate (>=0.8.7)
